rdmi/__init__.py
rdmi/rdmi.py
rdmi-1.0.1.dist-info/AUTHORS
rdmi-1.0.1.dist-info/LICENSE
rdmi-1.0.1.dist-info/METADATA
rdmi-1.0.1.dist-info/WHEEL
rdmi-1.0.1.dist-info/entry_points.txt
rdmi-1.0.1.dist-info/top_level.txt
rdmi-1.0.1.dist-info/RECORD
