Metadata-Version: 2.1
Name: rdmi
Version: 1.0.1
Summary: Print a range of numbers in random order
Home-page: https://github.com/Teal-Projects/rdmi
Author: Kanchen Monnin
Author-email: kanchen@mail.com
License: UNKNOWN
Platform: UNKNOWN
Classifier: Programming Language :: Python
Classifier: Development Status :: 3 - Alpha
Classifier: Intended Audience :: Developers
Classifier: Topic :: Software Development :: Build Tools
Classifier: License :: OSI Approved :: MIT License
Classifier: Programming Language :: Python :: 3
Classifier: Programming Language :: Python :: 3.4
Classifier: Programming Language :: Python :: 3.5
Classifier: Programming Language :: Python :: 3.6
Requires-Dist: random
Requires-Dist: sys
